{
  "id": "light_hammer",
  "size": 16,
  "outputs": {
    "light_hammer": "iron",
    "light_hammer_diamond": "diamond",
    "light_hammer_netherite": "netherite"
  },
  "rows": [
    "................",
    "................",
    "...........sBBg.",
    "..........sBBgg.",
    ".........ssBg...",
    "..........ff....",
    ".........ww.....",
    "........ww......",
    ".......ww.......",
    "......ww........",
    ".....kk.........",
    "....kk..........",
    ".....f..........",
    "................",
    "................",
    "................"
  ]
}
